wiegand_calculator/__init__.py
wiegand_calculator/wiegand.py
wiegand_calculator-0.0.1.dist-info/METADATA
wiegand_calculator-0.0.1.dist-info/WHEEL
wiegand_calculator-0.0.1.dist-info/licenses/LICENSE
wiegand_calculator-0.0.1.dist-info/RECORD
