Metadata-Version: 2.3
Name: wiegand_calculator
Version: 0.0.1
Summary: A simple converter for Wiegand data
Project-URL: Homepage, https://github.com/tachoknight/wiegand-calculator/tree/master/python
Project-URL: Issues, https://github.com/tachoknight/wiegand-calculator/issues
Author-email: Ron Olson <tachoknight@gmail.com>
Classifier: License :: CC0 1.0 Universal (CC0 1.0) Public Domain Dedication
Classifier: Operating System :: OS Independent
Classifier: Programming Language :: Python :: 3
Requires-Python: >=3.8
